[{"Name":"Sunflower Seeds","Country":"Spain","Season":1},{"Name":"Beet Root","Country":"Ukraine","Season":2},{"Name":"Sunflower Seeds","Country":"Spain","Season":2},{"Name":"Corn","Country":"Spain","Season":1},{"Name":"Sunflower Seeds","Country":"Ukraine","Season":2},{"Name":"Sunflower Seeds","Country":"Spain","Season":2},{"Name":"Beet Root","Country":"Netherlands","Season":3},{"Name":"Corn","Country":"Poland","Season":3},{"Name":"Corn","Country":"Netherlands","Season":2},{"Name":"Corn","Country":"Netherlands","Season":2},{"Name":"Sunflower Seeds","Country":"Poland","Season":1},{"Name":"Corn","Country":"Spain","Season":2},{"Name":"Sunflower Seeds","Country":"Netherlands","Season":1},{"Name":"Carrot","Country":"Ukraine","Season":3},{"Name":"Carrot","Country":"Ukraine","Season":3}]